ledmap/__init__.py
ledmap/matrix.py
ledmap/py.typed
ledmap/util.py
ledmap-0.1.dist-info/WHEEL
ledmap-0.1.dist-info/METADATA
ledmap-0.1.dist-info/RECORD
