Metadata-Version: 2.4
Name: ledmap
Version: 0.1
Summary: LED pixel mapper
Author: James Myatt
Author-email: James Myatt <james@jamesmyatt.co.uk>
License-Expression: MIT
Classifier: Development Status :: 3 - Alpha
Classifier: Intended Audience :: Developers
Classifier: Operating System :: OS Independent
Classifier: Programming Language :: Python :: 3.13
Classifier: Programming Language :: Python :: 3.14
Requires-Python: >=3.13
